soilprofilecollection/.gitignore
soilprofilecollection/__init__.py
soilprofilecollection/soil_profile_collection.py
soilprofilecollection-0.3.0.dist-info/LICENSE.md
soilprofilecollection-0.3.0.dist-info/METADATA
soilprofilecollection-0.3.0.dist-info/WHEEL
soilprofilecollection-0.3.0.dist-info/RECORD
