Metadata-Version: 2.1
Name: soilprofilecollection
Version: 0.3.0
Summary: A 'Python' implementation of the 'SoilProfileCollection' object from the 'R' package 'aqp'
Author: Andrew Gene Brown
Author-email: brown.andrewg@gmail.com
Requires-Python: >=3.10
Classifier: Programming Language :: Python :: 3
Classifier: Programming Language :: Python :: 3.10
Classifier: Programming Language :: Python :: 3.11
Classifier: Programming Language :: Python :: 3.12
Provides-Extra: plot
Requires-Dist: matplotlib (>=3.10.1,<4.0.0) ; extra == "plot"
Requires-Dist: numpy (>=2.2.4,<3.0.0)
Requires-Dist: pandas (>=2.2.3,<3.0.0)
